odoo/addons/base_remote/README.rst
odoo/addons/base_remote/__init__.py
odoo/addons/base_remote/__manifest__.py
odoo/addons/base_remote/i18n/base_remote.pot
odoo/addons/base_remote/i18n/es.po
odoo/addons/base_remote/models/__init__.py
odoo/addons/base_remote/models/base.py
odoo/addons/base_remote/models/res_remote.py
odoo/addons/base_remote/models/res_users.py
odoo/addons/base_remote/security/ir.model.access.csv
odoo/addons/base_remote/tests/__init__.py
odoo/addons/base_remote/tests/test_remote.py
odoo/addons/base_remote/views/res_remote_views.xml
odoo11_addon_base_remote-11.0.1.0.4.dist-info/METADATA
odoo11_addon_base_remote-11.0.1.0.4.dist-info/RECORD
odoo11_addon_base_remote-11.0.1.0.4.dist-info/WHEEL
odoo11_addon_base_remote-11.0.1.0.4.dist-info/top_level.txt
